apiverve_countydatalookup/__init__.py
apiverve_countydatalookup/apiClient.py
apiverve_countydatalookup/exceptions.py
apiverve_countydatalookup/setup.py
apiverve_countydatalookup/setup_dep.py
apiverve_countydatalookup/tests/__init__.py
apiverve_countydatalookup/tests/test_api.py
apiverve_countydatalookup-1.1.7.dist-info/LICENSE
apiverve_countydatalookup-1.1.7.dist-info/METADATA
apiverve_countydatalookup-1.1.7.dist-info/WHEEL
apiverve_countydatalookup-1.1.7.dist-info/top_level.txt
apiverve_countydatalookup-1.1.7.dist-info/RECORD
